quranbot_schema_registry/__init__.py
quranbot_schema_registry/schemas/ayat/changed/1.json
quranbot_schema_registry/schemas/button/pushed/1.json
quranbot_schema_registry/schemas/daily_content/created/1.json
quranbot_schema_registry/schemas/file/send_triggered/1.json
quranbot_schema_registry/schemas/mailing/created/1.json
quranbot_schema_registry/schemas/mailing/daily_ayats/1.json
quranbot_schema_registry/schemas/mailing/daily_prayers/1.json
quranbot_schema_registry/schemas/mailing/deleted/1.json
quranbot_schema_registry/schemas/messages/created/1.json
quranbot_schema_registry/schemas/messages/deleted/1.json
quranbot_schema_registry/schemas/messages/deleted/2.json
quranbot_schema_registry/schemas/notification/created/1.json
quranbot_schema_registry/schemas/prayers/created/1.json
quranbot_schema_registry/schemas/prayers/created/2.json
quranbot_schema_registry/schemas/user/check_status/1.json
quranbot_schema_registry/schemas/user/reactivated/1.json
quranbot_schema_registry/schemas/user/subscribed/1.json
quranbot_schema_registry/schemas/user/unsubscribed/1.json
quranbot_schema_registry/schemas/websocket/notificationcreated/1.json
quranbot_schema_registry/validate_schema.py
quranbot_schema_registry-0.0.28.dist-info/METADATA
quranbot_schema_registry-0.0.28.dist-info/WHEEL
quranbot_schema_registry-0.0.28.dist-info/RECORD
