Metadata-Version: 2.1
Name: quranbot-schema-registry
Version: 0.0.28
Summary: quranbot-schema-registry
Author: Almaz Ilaletdinov
Author-email: a.ilaletdinov@yandex.ru
Requires-Python: >=3.9,<4.0
Classifier: Programming Language :: Python :: 3
Classifier: Programming Language :: Python :: 3.9
Classifier: Programming Language :: Python :: 3.10
Classifier: Programming Language :: Python :: 3.11
Classifier: Programming Language :: Python :: 3.12
Requires-Dist: jsonschema (>=4.7.2,<5.0.0)
